omixvizpy/__init__.py
omixvizpy/pca_plotting.py
omixvizpy-0.1.2.dist-info/METADATA
omixvizpy-0.1.2.dist-info/WHEEL
omixvizpy-0.1.2.dist-info/licenses/LICENSE
omixvizpy-0.1.2.dist-info/RECORD
