Metadata-Version: 2.4
Name: omixvizpy
Version: 0.1.2
Summary: A Python package for omics data visualization with a focus on PCA plotting
Project-URL: Homepage, https://github.com/Leslie-Lu/omixvizpy
Project-URL: Bug Reports, https://github.com/Leslie-Lu/omixvizpy/issues
Project-URL: Source, https://github.com/Leslie-Lu/omixvizpy
Project-URL: Documentation, https://github.com/Leslie-Lu/omixvizpy#readme
Author-email: Zhen Lu <luzh29@mail2.sysu.edu.cn>
Maintainer-email: Zhen Lu <luzh29@mail2.sysu.edu.cn>
License: MIT License
License-File: LICENSE
Keywords: bioinformatics,data visualization,omics,pca,plotting,principal component analysis,visualization
Classifier: Development Status :: 3 - Alpha
Classifier: Intended Audience :: Science/Research
Classifier: License :: OSI Approved :: MIT License
Classifier: Operating System :: OS Independent
Classifier: Programming Language :: Python :: 3
Classifier: Programming Language :: Python :: 3.8
Classifier: Programming Language :: Python :: 3.9
Classifier: Programming Language :: Python :: 3.10
Classifier: Programming Language :: Python :: 3.11
Classifier: Programming Language :: Python :: 3.12
Classifier: Topic :: Scientific/Engineering :: Bio-Informatics
Classifier: Topic :: Scientific/Engineering :: Visualization
Requires-Python: >=3.8
Requires-Dist: matplotlib>=3.3.0
Requires-Dist: numpy>=1.20.0
Requires-Dist: pandas>=1.3.0
Requires-Dist: seaborn>=0.11.0
Provides-Extra: dev
Requires-Dist: black; extra == 'dev'
Requires-Dist: flake8; extra == 'dev'
Requires-Dist: mypy; extra == 'dev'
Requires-Dist: pre-commit; extra == 'dev'
Requires-Dist: pytest-cov; extra == 'dev'
Requires-Dist: pytest>=6.0; extra == 'dev'
Provides-Extra: docs
Requires-Dist: myst-parser; extra == 'docs'
Requires-Dist: sphinx-rtd-theme; extra == 'docs'
Requires-Dist: sphinx>=4.0; extra == 'docs'
